xoadmin/__init__.py
xoadmin/__main__.py
xoadmin/api/api.py
xoadmin/api/error.py
xoadmin/api/host.py
xoadmin/api/manager.py
xoadmin/api/storage.py
xoadmin/api/user.py
xoadmin/api/vm.py
xoadmin/api/websocket.py
xoadmin/cli/__init__.py
xoadmin/cli/apply.py
xoadmin/cli/auth.py
xoadmin/cli/cli.py
xoadmin/cli/config.py
xoadmin/cli/hosts.py
xoadmin/cli/model.py
xoadmin/cli/options.py
xoadmin/cli/storage.py
xoadmin/cli/users.py
xoadmin/cli/utils.py
xoadmin/cli/vms.py
xoadmin/configurator/__init__.py
xoadmin/configurator/config.py
xoadmin/configurator/configurator.py
xoadmin/configurator/loader.py
xoadmin/utils.py
xoadmin-1.2.4.dist-info/LICENSE
xoadmin-1.2.4.dist-info/METADATA
xoadmin-1.2.4.dist-info/WHEEL
xoadmin-1.2.4.dist-info/entry_points.txt
xoadmin-1.2.4.dist-info/RECORD
